small_view_set/README.md
small_view_set/__init__.py
small_view_set/config.py
small_view_set/decorators.py
small_view_set/exceptions.py
small_view_set/helpers.py
small_view_set/small_view_set.py
django_small_view_set-1.0.0.dist-info/LICENSE
django_small_view_set-1.0.0.dist-info/METADATA
django_small_view_set-1.0.0.dist-info/WHEEL
django_small_view_set-1.0.0.dist-info/RECORD
