Metadata-Version: 2.1
Name: django-small-view-set
Version: 1.0.0
Summary: A lightweight and explicit Django ViewSet alternative with minimal abstraction and full async support
Home-page: https://github.com/nateonguitar/django-small-view-set
License: MIT
Keywords: django,viewset,view set,api,async,rest api,django async,lightweight
Author: Nate Brooks
Requires-Python: >=3.8
Classifier: License :: OSI Approved :: MIT License
Classifier: Programming Language :: Python :: 3
Classifier: Programming Language :: Python :: 3.8
Classifier: Programming Language :: Python :: 3.9
Classifier: Programming Language :: Python :: 3.10
Classifier: Programming Language :: Python :: 3.11
Requires-Dist: django (>=3.2)
Project-URL: Repository, https://github.com/nateonguitar/django-small-view-set
